casPYan/__init__.py
casPYan/edge.py
casPYan/feedforward.py
casPYan/network.py
casPYan/node.py
casPYan/processor.py
casPYan/util.py
casPYan/ende/rate.py
caspyan-0.2.1.dist-info/licenses/LICENSE
caspyan-0.2.1.dist-info/METADATA
caspyan-0.2.1.dist-info/WHEEL
caspyan-0.2.1.dist-info/top_level.txt
caspyan-0.2.1.dist-info/RECORD
